<mvc:View controllerName="com.proallone.voca.controller.App" displayBlock="true"
    xmlns:mvc="sap.ui.core.mvc"
    xmlns="sap.m"
    xmlns:tnt="sap.tnt"
    xmlns:core="sap.ui.core"
    core:require="{formatter: 'com/proallone/voca/model/Formatter'}">
    <tnt:ToolPage id="toolPage" sideExpanded="false">
        <tnt:header>
            <tnt:ToolHeader id="_IDGenToolHeader1" design="Solid" height="4rem">
                <!-- <Button id="sideNavigationToggleButton" icon="sap-icon://menu2" type="Transparent" press="onSideNavButtonPress">
                    <layoutData>
                        <OverflowToolbarLayoutData priority="NeverOverflow" />
                    </layoutData>
                </Button> -->
                <Image id="_IDGenImage" src="static/images/voca.png" decorative="false" press="onLogoPressed" tooltip="{i18n>tlpEventsLogo}" height="40px">
                    <layoutData>
                        <OverflowToolbarLayoutData id="_IDGenOverflowToolbarLayoutData" priority="NeverOverflow"/>
                    </layoutData>
                </Image>
                <Title id="_IDGenTitle" text="{i18n>ttlEventsTitle}" wrapping="false" class="title">
                    <layoutData>
                        <OverflowToolbarLayoutData id="_IDGenOverflowToolbarLayoutData1" priority="Disappear"/>
                    </layoutData>
                </Title>
                <tnt:ToolHeaderUtilitySeparator id="_IDGenToolHeaderUtilitySeparator2"/>

                <ToolbarSpacer id="_IDGenToolbarSpacer" />
                <tnt:ToolHeaderUtilitySeparator id="_IDGenToolHeaderUtilitySeparator"/>
                <Button id="_IDGenButton2" icon="sap-icon://bell" type="Transparent" tooltip="{i18n>tlpNotifications}" press="onNotificationsPress">
                    <customData>
                        <BadgeCustomData id="_IDGenBadgeCustomData" key="badge" value="{path : 'notifications',  formatter: 'formatter.countNotViewedNotifications'}" visible="true"/>
                    </customData>
                    <layoutData>
                        <OverflowToolbarLayoutData id="_IDGenOverflowToolbarLayoutData5" priority="NeverOverflow"/>
                    </layoutData>
                </Button>
                <OverflowToolbarButton id="_IDGenOverflowToolbarButton" icon="sap-icon://grid" type="Transparent" tooltip="{i18n>tlpActions}" press="onActionsPress"/>
                <Avatar id="_IDGenAvatar" src="test-resources/sap/m/images/dronning_victoria.jpg" displaySize="S" press="onAvatarPressed" tooltip="{i18n>tlpProfile}">
                    <layoutData>
                        <OverflowToolbarLayoutData id="_IDGenOverflowToolbarLayoutData2" priority="NeverOverflow"/>
                    </layoutData>
                </Avatar>
            </tnt:ToolHeader>
        </tnt:header>
        <!-- <tnt:subHeader>
            <tnt:ToolHeader id="_IDGenToolHeader">
                <Breadcrumbs id="_IDGenBreadcrumbs" currentLocation="Events" separatorStyle="GreaterThan">
                    <Link id="_IDGenLink" text="Events" press="onBreadcrumbPress">
                        <customData>
                            <core:CustomData id="_IDGenCustomData" key="target" value="RouteEvents"/>
                        </customData>
                    </Link>
                </Breadcrumbs>
            </tnt:ToolHeader>
        </tnt:subHeader> -->
        
        <!-- <tnt:sideContent>
            <tnt:SideNavigation expanded="false" itemSelect="onItemSelect">
                <tnt:NavigationList>
                    <tnt:NavigationListItem text="Events" icon="sap-icon://calendar" enabled="true" selectable="true" key="key1"/>
                </tnt:NavigationList>
                <tnt:fixedItem>
                    <tnt:NavigationList>
                        <tnt:NavigationListItem text="About" icon="sap-icon://hint" press="onQuickActionPress" selectable="true"/>
                    </tnt:NavigationList>
                </tnt:fixedItem>
            </tnt:SideNavigation>
        </tnt:sideContent> -->
        <tnt:mainContents>
            <App id="app"/>
        </tnt:mainContents>
    </tnt:ToolPage>
</mvc:View>